{
  "timestamp": "2025-09-14T16:38:16.386833",
  "cache_key": "2f23dc253f55ec795e4dd410e219480a",
  "metadata": {
    "keywords": "Data Scientist",
    "location": "New York, NY",
    "max_jobs": 10,
    "job_type_filter": null,
    "category_filter": null,
    "trusted_only": true,
    "scraped_at": "2025-09-14T16:38:16.386833"
  },
  "job_count": 6,
  "data": [
    {
      "title": "Data Scientist, Product",
      "company": "Notion",
      "location": "New York, NY",
      "description": "About UsNotion helps you build beautiful tools for your life’s work. In today's world of endless apps and tabs, Notion provides one place for teams to get everything done, seamlessly connecting docs, notes, projects, calendar, and email—with AI built in to find answers and automate work. Millions of users, from individuals to large organizations like Toyota, Figma, and OpenAI, love Notion for its flexibility and choose it because it helps them save time and money.In-person collaboration is essential to Notion's culture. We require all team members to work from our offices on Mondays and Thursdays, our designated Anchor Days. Certain teams or positions may require additional in-office workdays.About The RoleNotion’s mission is to make toolmaking ubiquitous. We are rapidly growing our business to empower every individual to build their own tools, block by block. Truth-seeking is one of Notion’s values, and it lies at the heart of the product data science team’s foundation. Data scientists on this team work closely with engineering teams to transform data into evidence that can direct product decisions.As an member of the product data science team, you'll be instrumental in setting the roadmap for how product, engineering, and data science work together, and then doing the hands on work to execute against it. There will be significant variation from one day to the next, but whether you're exploring what a successful Notion account looks like, analyzing user behavior on a feature to identify areas of improvement, or running experiments to evaluate the success of a key feature launch, you'll absolutely impact the development of Notion.What You'll AchieveYou will apply your expertise in statistical inference, data analysis, and the presentation of data to see beyond the numbers and understand how our users interact with NotionYou will dive into ambiguous areas, define problems and opportunities for the team to work on the next influential projectYou'll design the right set of experiments or analyses to evaluate the success of new featuresYou'll partner closely with a product, engineering, and marketing pillar at every step of the development process, driving forward data science and analytics work in that area.You'll work with your teams to determine both north star and operational metrics, and build and maintain the dashboards that those teams rely on for monitoring progress and making key decisions.You'll influence your product roadmap by communicating your findings with the rest of the company, and driving and verifying change in our product and business. (Insights are useful. Impact is even better!)Skills You'll Need To BringYou have spent meaningful time as a data scientist partnering with product and engineering teams. You can draw on that experience to identify where data can have the most impact and clearly communicate to your partner teams what that impact is.You have expertise in SQL and at least one scripting language (ideally Python or R).You know how to use statistical inference and experimentation to drive actionable recommendations.You have experience building predictive models, and you know how to evaluate their effectiveness.You are comfortable transforming raw data to build your own data sets if the measure you need doesn't exist yet.You have a bias for using the right tools to get a job done with maximum efficiency. You have experience making tradeoffs between speed and accuracy.We hire talented and passionate people from a variety of backgrounds because we want our global employee base to represent the wide diversity of our customers. If you’re excited about a role but your past experience doesn’t align perfectly with every bullet point listed in the job description, we still encourage you to apply. If you’re a builder at heart, share our company values, and enthusiastic about making software toolmaking ubiquitous, we want to hear from you.Notion is proud to be an equal opportunity employer. We do not discriminate in hiring or any employment decision based on race, color, religion, national origin, age, sex (including pregnancy, childbirth, or related medical conditions), marital status, ancestry, physical or mental disability, genetic information, veteran status, gender identity or expression, sexual orientation, or other applicable legally protected characteristic. Notion considers qualified applicants with criminal histories, consistent with applicable federal, state and local law. Notion is also committed to providing reasonable accommodations for qualified individuals with disabilities and disabled veterans in our job application procedures. If you need assistance or an accommodation due to a disability, please let your recruiter know.Notion is committed to providing highly competitive cash compensation, equity, and benefits. The compensation offered for this role will be based on multiple factors such as location, the role’s scope and complexity, and the candidate’s experience and expertise, and may vary from the range provided below. For roles based in San Francisco or New York City, the estimated base salary range for this role is $140,000 - $170,000 per year.By clicking “Submit Application”, I understand and agree that Notion and its affiliates and subsidiaries will collect and process my information in accordance with Notion’s Global Recruiting Privacy Policy.",
      "requirements": [
        "essential to Notion's culture",
        "person collaboration is essential to Notion's culture"
      ],
      "job_type": "Full-time",
      "skills": [
        "Data Science",
        "Sql",
        "Python",
        "Express",
        "Less",
        "Ai",
        "R"
      ],
      "posted_date": "2025-08-30",
      "job_url": "https://www.linkedin.com/jobs/view/data-scientist-product-at-notion-4282332923?position=1&pageNum=0&refId=BDWq20clH0k%2BuytMC7XfTQ%3D%3D&trackingId=n6wj1ypCRW2zCKR8iXza2g%3D%3D",
      "salary": "$140,000.00/yr - $170,000.00/yr",
      "category": "Data Science & Analytics",
      "is_trusted_company": true,
      "experience_level": "Mid Level",
      "employment_type": "Full-time"
    },
    {
      "title": "Business Data Scientist, Machine Learning",
      "company": "Google",
      "location": "New York, NY",
      "description": "This role may also be located in our Playa Vista, CA campus.Applicants in the County of Los Angeles: Qualified applications with arrest or conviction records will be considered for employment in accordance with the Los Angeles County Fair Chance Ordinance for Employers and the California Fair Chance Act.Applicants in San Francisco: Qualified applications with arrest or conviction records will be considered for employment in accordance with the San Francisco Fair Chance Ordinance for Employers and the California Fair Chance Act.Note: By applying to this position you will have an opportunity to share your preferred working location from the following: Atlanta, GA, USA; New York, NY, USA; Los Angeles, CA, USA; San Francisco, CA, USA; Washington D.C., DC, USA; Mountain View, CA, USA.Minimum qualifications:Master's degree in a quantitative discipline such as Statistics, Engineering, Sciences, or equivalent practical experience.4 years of experience using analytics to solve product or business problems, coding (e.g., Python, R, SQL), querying databases or statistical analysis.Preferred qualifications:Experience designing and implementing causal ML models.Experience designing and building large datasets for ML modeling.Experience with statistical modeling packages.Excellent presentation skills.About The JobThe Global Business Strategy and Operations team is part of the Go-to-Market organization that makes sure Google's business pursues the best strategy and executes flawlessly. Team members are exceptional in business strategy and operations, are problem-solvers and strategic, yet highly pragmatic and results-oriented. This team architects the future of Google’s global ads business. The function drives Go-to-Market strategy and analytics, operational efficiency and productivity, risk and compliance, Chief Business Officer and Chief of Staff team, and ads policy strategy.The Data, Insights, and Analytics (DIA) partners with various Global Business Strategy and Operations team members to drive the best decisions possible with data. We build creative and novel Machine Learning (ML) solutions and analyses to drive strategy. We help our organization make nuanced, smart, and difficult decisions to ensure the Ads Business continues to grow.In this role, you will be significantly improving how customers are assigned to the most optimal sales channel, as our current manual decision model, while nuanced, is limited by historical data and a narrow understanding of what drives customer performance. You will be tasked with developing a causal ML model to automate and enhance these assignments, while also uncovering new data patterns that could revolutionize how our business manages clients. You will need to be a strategic thinker, using your business and product judgment to guide our data strategy. Your problem-solving skills will be key to ideating, discovering, and integrating hundreds, if not thousands, of data signals, ensuring they are perfectly structured for our causal ML problem.The US base salary range for this full-time position is $166,000-$244,000 + bonus + equity + benefits. Our salary ranges are determined by role, level, and location. Within the range, individual pay is determined by work location and additional factors, including job-related skills, experience, and relevant education or training. Your recruiter can share more about the specific salary range for your preferred location during the hiring process.Please note that the compensation details listed in US role postings reflect the base salary only, and do not include bonus, equity, or benefits. Learn more about benefits at Google .ResponsibilitiesDevelop core dataset and signal repository, using SQL or other scripting language, for Machine Learning. Develop expansive dataset that describes the Google Ads Customer, in as much detail as reasonable, that will enable us to establish causal effects from our business efforts.Investigate, ideate, build, and streamline major signal repository to enable ML and unique insights.Analyze data, partner with other Business Data Scientists, to help us understand drivers of historical business performance. Leverage insights to determine areas of opportunity for improvement in business treatment.Build causal ML models to improve business channel assignments and treatment.Google is proud to be an equal opportunity workplace and is an affirmative action employer. We are committed to equal employment opportunity regardless of race, color, ancestry, religion, sex, national origin, sexual orientation, age, citizenship, marital status, disability, gender identity or Veteran status. We also consider qualified applicants regardless of criminal histories, consistent with legal requirements. See also Google's EEO Policy and EEO is the Law. If you have a disability or special need that requires accommodation, please let us know by completing our Accommodations for Applicants form .",
      "requirements": [
        "Master's degree in a quantitative discipline such as Sta",
        "Experience with statistical modeling packages",
        "Minimum qualifications:Master's degree in a quantitative discipline such as Statistics, Engineering, Sciences, or equivalent practical experience",
        "4 years of experience using analytics to solve product or business problems, coding (e",
        "Preferred qualifications:Experience designing and implementing causal ML models",
        "Your recruiter can share more about the specific salary range for your preferred location during the hiring process"
      ],
      "job_type": "Full-time",
      "skills": [
        "Machine Learning",
        "Sql",
        "Go",
        "Python",
        "Less",
        "Ai",
        "R"
      ],
      "posted_date": "2025-09-03",
      "job_url": "https://www.linkedin.com/jobs/view/business-data-scientist-machine-learning-at-google-4294804612?position=3&pageNum=0&refId=BDWq20clH0k%2BuytMC7XfTQ%3D%3D&trackingId=nyBEtKI1kM%2F35%2FEzStrbvA%3D%3D",
      "salary": "$166,000.00/yr - $244,000.00/yr",
      "category": "Data Science & Analytics",
      "is_trusted_company": true,
      "experience_level": "Mid Level",
      "employment_type": "Full-time"
    },
    {
      "title": "Data Scientist, Product Analytics",
      "company": "Meta",
      "location": "New York, NY",
      "description": "As a Data Scientist at Meta, you will shape the future of people-facing and business-facing products we build across our entire family of applications (Facebook, Instagram, Messenger, WhatsApp, Oculus). By applying your technical skills, analytical mindset, and product intuition to one of the richest data sets in the world, you will help define the experiences we build for billions of people and hundreds of millions of businesses around the world. You will collaborate on a wide array of product and business problems with a wide-range of cross-functional partners across Product, Engineering, Research, Data Engineering, Marketing, Sales, Finance and others. You will use data and analysis to identify and solve product development's biggest challenges. You will influence product strategy and investment decisions with data, be focused on impact, and collaborate with other teams. By joining Meta, you will become part of a world-class analytics community dedicated to skill development and career growth in analytics and beyond.Product leadership: You will use data to shape product development, quantify new opportunities, identify upcoming challenges, and ensure the products we build bring value to people, businesses, and Meta. You will help your partner teams prioritize what to build, set goals, and understand their product's ecosystem.Analytics: You will guide teams using data and insights. You will focus on developing hypotheses and employ a varied toolkit of rigorous analytical approaches, different methodologies, frameworks, and technical approaches to test them.Communication and influence: You won't simply present data, but tell data-driven stories. You will convince and influence your partners using clear insights and recommendations. You will build credibility through structure and clarity, and be a trusted strategic partner.Data Scientist, Product Analytics Responsibilities:Work with large and complex data sets to solve a wide array of challenging problems using different analytical and statistical approachesApply technical expertise with quantitative analysis, experimentation, data mining, and the presentation of data to develop strategies for our products that serve billions of people and hundreds of millions of businessesIdentify and measure success of product efforts through goal setting, forecasting, and monitoring of key product metrics to understand trendsDefine, understand, and test opportunities and levers to improve the product, and drive roadmaps through your insights and recommendationsPartner with Product, Engineering, and cross-functional teams to inform, influence, support, and execute product strategy and investment decisionsMinimum Qualifications:Bachelor's degree in Computer Science, Computer Engineering, relevant technical field, or equivalent practical experienceA minimum of 6 years of work experience in analytics (minimum of 4 years with a Ph.D.)Bachelor's degree in Mathematics, Statistics, a relevant technical field, or equivalent practical experienceExperience with data querying languages (e.g. SQL), scripting languages (e.g. Python), and/or statistical/mathematical software (e.g. R)Preferred Qualifications:Master's or Ph.D. Degree in a quantitative fieldAbout Meta:Meta builds technologies that help people connect, find communities, and grow businesses. When Facebook launched in 2004, it changed the way people connect. Apps like Messenger, Instagram and WhatsApp further empowered billions around the world. Now, Meta is moving beyond 2D screens toward immersive experiences like augmented and virtual reality to help build the next evolution in social technology. People who choose to build their careers by building with us at Meta help shape a future that will take us beyond what digital connection makes possible today—beyond the constraints of screens, the limits of distance, and even the rules of physics.Meta is proud to be an Equal Employment Opportunity and Affirmative Action employer. We do not discriminate based upon race, religion, color, national origin, sex (including pregnancy, childbirth, or related medical conditions), sexual orientation, gender, gender identity, gender expression, transgender status, sexual stereotypes, age, status as a protected veteran, status as an individual with a disability, or other applicable legally protected characteristics. We also consider qualified applicants with criminal histories, consistent with applicable federal, state and local law. Meta participates in the E-Verify program in certain locations, as required by law. Please note that Meta may leverage artificial intelligence and machine learning technologies in connection with applications for employment.Meta is committed to providing reasonable accommodations for candidates with disabilities in our recruiting process. If you need any assistance or accommodations due to a disability, please let us know at accommodations-ext@fb.com.$173,000/year to $242,000/year + bonus + equity + benefitsIndividual compensation is determined by skills, qualifications, experience, and location. Compensation details listed in this posting reflect the base hourly rate, monthly rate, or annual salary only, and do not include bonus, equity or sales incentives, if applicable. In addition to base compensation, Meta offers benefits. Learn more about  benefits  at Meta.",
      "requirements": [
        "Bachelor's degree in Computer Science, Computer Engineerin",
        "Bachelor's degree in Mathematics, Statistics, a relevant t",
        "Degree in a quantitative fieldAbout Meta:Meta builds tec",
        "Experience with data querying languages (e",
        "R)Preferred Qualifications:Master's or Ph",
        "Degree in a quantitative fieldAbout Meta:Meta builds technologies that help people connect, find communities, and grow businesses",
        "Verify program in certain locations, as required by law"
      ],
      "job_type": "Full-time",
      "skills": [
        "Rust",
        "Machine Learning",
        "Git",
        "Sql",
        "Go",
        "Python",
        "Express",
        "Ai",
        "R",
        "Artificial Intelligence"
      ],
      "posted_date": "2025-08-28",
      "job_url": "https://www.linkedin.com/jobs/view/data-scientist-product-analytics-at-meta-4290374137?position=5&pageNum=0&refId=BDWq20clH0k%2BuytMC7XfTQ%3D%3D&trackingId=cBDzNt9fuR2V960FJIyb%2BA%3D%3D",
      "salary": "$173,000.00/yr - $242,000.00/yr",
      "category": "Data Science & Analytics",
      "is_trusted_company": true,
      "experience_level": "Mid Level",
      "employment_type": "Full-time"
    },
    {
      "title": "Business Data Scientist, Impact Measurement",
      "company": "Google",
      "location": "New York, NY",
      "description": "Note: By applying to this position you will have an opportunity to share your preferred working location from the following: San Bruno, CA, USA; Mountain View, CA, USA; New York, NY, USA.Minimum qualifications:Master's degree in a STEM field or equivalent practical experience.3 years of industry or PhD Data Science experience.Experience in causal inference, A/B testing, statistical modeling, or Machine Learning.Experience in programming with SQL and Python, and in leveraging ML or statistical libraries (e.g. TensorFlow, Scikit-learn, XGBoost, Keras, Pandas).Preferred qualifications:PhD in a STEM field.Experience in a Data Science role supporting Sales, Marketing, or Customer Support.Experience in Natural Language Processing (NLP), Large Language Models (LLMs), Generative AI, and R.Experience drawing conclusions from data, breaking down technical concepts into simple terms, connecting with, and presenting to, technical and non-technical stakeholders, and recommending actions.Publications related to Data Science, posters or presentations in AI/ML conferences, or patents.About The JobAs a Business Data Scientist in YouTube Business Go-To-Market (GTM) Impact Measurement team you will work with business leaders to help shape the future of YouTube. You will have to leverage rigorous techniques from causal inference, advanced statistical modeling, and Machine Learning (ML). It will be your responsibility to determine the best approach for solving problems, and communicate clearly with decision-makers who may or may not have a strong technical background.You will be a detail-oriented problem-solver with broad knowledge of causal inference, Bayesian statistics, and ML. You will use a large set of tools from experimental to observational techniques, touching on a broad range of problems from different functional and product areas. You will be comfortable in taking on various roles, and be passionate about conducting causal studies and helping stakeholders implement data driven decisions. Creative problem-solving and stakeholder management skills are critical.Effective data scientists on this team keep up with advances in the causal inference literature. When available methodologies are not well suited for the problem you are trying to solve, you will be encouraged to develop new methods in collaboration with your teammates and work with the summer interns on research projects. You will also attend relevant conferences and organize internal events to keep the toolkit updated and to educate the broader Google community.Google Cloud accelerates every organization’s ability to digitally transform its business and industry. We deliver enterprise-grade solutions that leverage Google’s cutting-edge technology, and tools that help developers build more sustainably. Customers in more than 200 countries and territories turn to Google Cloud as their trusted partner to enable growth and solve their most critical business problems.The US base salary range for this full-time position is $141,000-$202,000 + bonus + equity + benefits. Our salary ranges are determined by role, level, and location. Within the range, individual pay is determined by work location and additional factors, including job-related skills, experience, and relevant education or training. Your recruiter can share more about the specific salary range for your preferred location during the hiring process.Please note that the compensation details listed in US role postings reflect the base salary only, and do not include bonus, equity, or benefits. Learn more about benefits at Google .ResponsibilitiesDesign and execute causal studies to address critical business questions.Leverage advanced statistical models to find business insights in experimental and observational data.Present and communicate actionable insights and recommendations to executives and cross-functional partners.Serve as a peer reviewer and consultant for causal studies across the organization.Google is proud to be an equal opportunity workplace and is an affirmative action employer. We are committed to equal employment opportunity regardless of race, color, ancestry, religion, sex, national origin, sexual orientation, age, citizenship, marital status, disability, gender identity or Veteran status. We also consider qualified applicants regardless of criminal histories, consistent with legal requirements. See also Google's EEO Policy and EEO is the Law. If you have a disability or special need that requires accommodation, please let us know by completing our Accommodations for Applicants form .",
      "requirements": [
        "Master's degree in a STEM field or equivalent practical",
        "PhD Data Science experience",
        "PhD in a STEM field",
        "knowledge of causal inference, Bayesian statistics, and ML",
        "Minimum qualifications:Master's degree in a STEM field or equivalent practical experience",
        "Preferred qualifications:PhD in a STEM field",
        "Your recruiter can share more about the specific salary range for your preferred location during the hiring process"
      ],
      "job_type": "Full-time",
      "skills": [
        "Rust",
        "Machine Learning",
        "Data Science",
        "Pandas",
        "Git",
        "Scikit-Learn",
        "Sql",
        "Go",
        "Python",
        "Keras",
        "Less",
        "Tensorflow"
      ],
      "posted_date": "2025-09-01",
      "job_url": "https://www.linkedin.com/jobs/view/business-data-scientist-impact-measurement-at-google-4293581063?position=8&pageNum=0&refId=BDWq20clH0k%2BuytMC7XfTQ%3D%3D&trackingId=kT7x3lw9cooIMq6ZmNZloA%3D%3D",
      "salary": "$141,000.00/yr - $202,000.00/yr",
      "category": "Data Science & Analytics",
      "is_trusted_company": true,
      "experience_level": "Mid Level",
      "employment_type": "Full-time"
    },
    {
      "title": "Data Scientist, Campus, United States - BCG X",
      "company": "BCG X",
      "location": "New York, NY",
      "description": "Locations: Boston | Chicago | Washington | Pittsburgh | New York | Brooklyn | Manhattan Beach | Dallas | Miami | San Francisco | Seattle | Los AngelesWho We AreBoston Consulting Group partners with leaders in business and society to tackle their most important challenges and capture their greatest opportunities. BCG was the pioneer in business strategy when it was founded in 1963. Today, we help clients with total transformation-inspiring complex change, enabling organizations to grow, building competitive advantage, and driving bottom-line impact.To succeed, organizations must blend digital and human capabilities. Our diverse, global teams bring deep industry and functional expertise and a range of perspectives to spark change. BCG delivers solutions through leading-edge management consulting along with technology and design, corporate and digital ventures—and business purpose. We work in a uniquely collaborative model across the firm and throughout all levels of the client organization, generating results that allow our clients to thrive.We Are BCG XWe’re a diverse team of more than 3,000 tech experts united by a drive to make a difference. Working across industries and disciplines, we combine our experience and expertise to tackle the biggest challenges faced by society today. We go beyond what was once thought possible, creating new and innovative solutions to the world’s most complex problems. Leveraging BCG’s global network and partnerships with leading organizations, BCG X provides a stable ecosystem for talent to build game-changing businesses, products, and services from the ground up, all while growing their career. Together, we strive to create solutions that will positively impact the lives of millions.What You'll DoOur BCG X teams own the full analytics value-chain end to end: framing new business challenges, designing innovative algorithms, implementing, and deploying scalable solutions, and enabling colleagues and clients to fully embrace AI. Our product offerings span from fully custom-builds to industry specific leading edge AI software solutions.As a Data Scientist, you'll be part of our rapidly growing team. You'll have the chance to apply data science methods and analytics to real-world business situations across a variety of industries to drive significant business impact. You'll have the chance to partner with clients in a variety of BCG regions and industries, and on key topics like climate change, enabling them to design, build, and deploy new and innovative solutions.Additional responsibilities will include developing and delivering thought leadership in scientific communities and papers as well as leading conferences on behalf of BCG X. Successful candidates are intellectually curious builders who are biased toward action, scrappy, and communicative.We Are Looking For Talented Individuals With a Passion For Data Science, Statistics, Operations Research And Transforming Organizations Into AI Led Innovative Companies. Successful Candidates Possess The FollowingComfortable in a client-facing role with the ambition to lead teams Likes to distill complex results or processes into simple, clear visualizations Explain sophisticated data science concepts in an understandable manner Love building things and are comfortable working with modern development tools and writing code collaboratively (bonus points if you have a software development or DevOps experience) Significant experience applying advanced analytics to a variety of business situations and a proven ability to synthesize complex data Deep understanding of modern machine learning techniques and their mathematical underpinnings, and can translate this into business implications for our clients Have strong project management skills What You'll BringThis position is open to students currently pursuing a full-time Bachelors or Masters degree and graduating between December 2025 - August 2026. The deadline to apply for this position is September 16, 2025 at 11:59pm ET.TechnologiesProgramming Languages: PythonAdditional infoYou must live within a reasonable commuting distance of your home office. As a member of that office, it is expected you will be in the office as directed. This role puts you on an accelerated path of personal and professional growth and development and so, at times, requires extended working hours. Our work often requires travel to client sites.The first-year base compensation for this role is ranges from $110,000 - $160,000 USD.At BCG, We Are Committed To Offering a Comprehensive Benefit Program That Includes Everything Our Employees And Their Families Need To Be Well And Live Life To The Fullest. We Pay The Full Cost Of Medical, Dental, And Vision Coverage For Employees – And Their Eligible Family Members. * That’s Zero Dollars In Premiums Taken From Employee Paychecks. All Our Plans Provide Best In Class CoverageZero-dollar ($0) health insurance premiums for BCG employees, spouses, and children Low $10 (USD) copays for trips to the doctor, urgent care visits and prescriptions for generic drugs Dental coverage, including up to $5,000 in orthodontia benefits Vision insurance with coverage for both glasses and contact lenses annually Reimbursement for gym memberships and other fitness activities Fully vested Profit-Sharing Retirement Fund contributions made annually, whether you contribute or not, plus the option for employees to make personal contributions to a 401(k) plan Paid Parental Leave and other family benefits such as elective egg freezing, surrogacy, and adoption reimbursement Generous paid time off including 12 holidays per year, an annual office closure between Christmas and New Years, and 15 vacation days per year (earned at 1.25 days per month) Paid sick time on an as needed basis Employees, spouses, and children are covered at no cost. Employees share in the cost of domestic partner coverage.#BCGXjobBoston Consulting Group is an Equal Opportunity Employer. All qualified applicants will receive consideration for employment without regard to race, color, age, religion, sex, sexual orientation, gender identity / expression, national origin, disability, protected veteran status, or any other characteristic protected under national, provincial, or local law, where applicable, and those with criminal histories will be considered in a manner consistent with applicable state and local laws.BCG is an E - Verify Employer. Click here  for more information on E-Verify.",
      "requirements": [
        "Bachelors or Masters degree and graduating between Decembe",
        "time Bachelors or Masters degree and graduating between December 2025"
      ],
      "job_type": "Full-time",
      "skills": [
        "Data Science",
        "Machine Learning",
        "Git",
        "Go",
        "Spark",
        "Python",
        "Express",
        "Scala",
        "Ai",
        "Aws",
        "R"
      ],
      "posted_date": "2025-08-30",
      "job_url": "https://www.linkedin.com/jobs/view/data-scientist-campus-united-states-bcg-x-at-bcg-x-4281395634?position=6&pageNum=2&refId=A0J4prY9Dp%2BKOnn4LfnGlQ%3D%3D&trackingId=jJ7vVvCZLlMR017wjtOuTA%3D%3D",
      "salary": "$110,000.00/yr - $160,000.00/yr",
      "category": "Data Science & Analytics",
      "is_trusted_company": true,
      "experience_level": "Mid Level",
      "employment_type": "Full-time"
    },
    {
      "title": "Data Scientist Co-Op",
      "company": "Bristol Myers Squibb",
      "location": "Summit, NJ",
      "description": "Working with UsChallenging. Meaningful. Life-changing. Those aren't words that are usually associated with a job. But working at Bristol Myers Squibb is anything but usual. Here, uniquely interesting work happens every day, in every department. From optimizing a production line to the latest breakthroughs in cell therapy, this is work that transforms the lives of patients, and the careers of those who do it. You'll get the chance to grow and thrive through opportunities uncommon in scale and scope, alongside high-achieving teams. Take your career farther than you thought possible.Bristol Myers Squibb recognizes the importance of balance and flexibility in our work environment. We offer a wide variety of competitive benefits, services and programs that provide our employees with the resources to pursue their goals, both at work and in their personal lives. Read more careers.bms.com/working-with-us .Position SummaryThe Data Scientist Co-Op Student will play a crucial role in supporting analytics utilized by GPS' Cell Therapy Development and Operations (CTDO) organization. This role will contribute to our team's mission to establish and advance our process monitoring, analytics, and modeling ecosystem to support improved process design, risk management, continuous improvement, and investigations. The Data Scientist Co-Op Student will help ensure that our analytics meet business requirements and function in a robust, and operationally resilient manner. This role will have opportunities to build new or enhance existing analytics and/or help advance new/existing capabilities in predictive modelling (e.g. continue drivers analysis for existing Critical-to-Quality Attributes (CQAs), expand model to new CQAs, etc) and statistical process control (SPC). The Data Scientist Co-Op Student should have a strong interest in solving business problems, and an eagerness to work on all parts of the analytics value chain, from partnering with IT on data pipelines to operationalizing predictive models in the service of our patients around the world.The full-time co-op will take place January - June 2026.Key ResponsibilitiesCollaborate with stakeholders to identify business problems, goals, and KPIs to design, establish and maintain data products, predictive models, and business facing reports and dashboards.Contribute to testing, documentation of testing artifacts, and validation of Cell Therapy Data Products (e.g. Process Control and Product Quality etc.)Create or Update data flow diagrams and end-user training documentationIdentify and implement enhancement and automation of high-value analytics while ensuring they continue to function efficiently.Prepare reports, dashboards, and presentations to communicate analyses to stakeholders at various levels of the organization.Gather and prepare data using a combination of Python, SQL, or R from GPS source systemsFollow technical best practices in building, maintaining, and enhancing analytics output with scalable solutions, including code version control, pipeline management, deployment, and documentation.Qualifications & ExperienceCurrently pursuing or completed a Bachelor's or Master's degree in data analytics, engineering, mathematics, statistics, or life sciences discipline (e.g. Biology, Microbiology, Chemistry, Biochemistry etc.)Experience working with large datasets, data visualization tools, statistical software packages and platforms (specifically R, Python, SQL, Domino, AWS, GitHub, PowerBI, Tableau)Prior experience in a data and analytics role, including direct development experience a plusExperience with platforms or applications such as SAP, Benchling, LIMS, Veeva Quality Vault, MES is a plusExperience with biotech product development, manufacturing operations, supply chain, and quality control is a plusAll candidates must be authorized to work in the US both at the time of hire and for the duration of their employment. Please note that immigration or visa sponsorship is not available for this position.This is a temporary, time-bound position intended for the duration of the internship or co-op program. Employment in this role does not imply or guarantee ongoing or permanent employment with BMS.The starting hourly compensation for this assignment is within the range of $23.00 to $42.00/hr. Please note that the final individual compensation and any applicable benefits will be determined by your employer of record (and not BMS). Factors influencing this decision may include the characteristics of the assignment, such as demonstrated experience, required skill, and the geographic location of the job. Compensation details are subject to change.If you come across a role that intrigues you but doesn't perfectly line up with your resume, we encourage you to apply anyway. You could be one step away from work that will transform your life and career.Compensation OverviewThe starting compensation range(s) for this role are listed above for a full-time employee (FTE) basis. Additional incentive cash and stock opportunities (based on eligibility) may be available. The starting pay rate takes into account characteristics of the job, such as required skills, where the job is performed, the employee's work schedule, job-related knowledge, and experience. Final, individual compensation will be decided based on demonstrated experience.Eligibility for specific benefits listed on our careers site may vary based on the job and location. For more on benefits, please visit https //careers.bms.com/life-at-bms/.Benefit offerings are subject to the terms and conditions of the applicable plans then in effect and may include the following Medical, pharmacy, dental and vision care. Wellbeing support such as the BMS Living Life Better program and employee assistance programs (EAP). Financial well-being resources and a 401(K). Financial protection benefits such as short- and long-term disability, life insurance, supplemental health insurance, business travel protection and survivor support. Work-life programs include paid national holidays and optional holidays, Global Shutdown Days between Christmas and New Year's holiday, up to 120 hours of paid vacation, up to two (2) paid days to volunteer, sick time off, and summer hours flexibility. Parental, caregiver, bereavement, and military leave. Family care services such as adoption and surrogacy reimbursement, fertility/infertility benefits, support for traveling mothers, and child, elder and pet care resources. Other perks like tuition reimbursement and a recognition program.Uniquely Interesting Work, Life-changing CareersWith a single vision as inspiring as Transforming patients' lives through science™ , every BMS employee plays an integral role in work that goes far beyond ordinary. Each of us is empowered to apply our individual talents and unique perspectives in a supportive culture, promoting global participation in clinical trials, while our shared values of passion, innovation, urgency, accountability, inclusion and integrity bring out the highest potential of each of our colleagues.On-site ProtocolBMS has an occupancy structure that determines where an employee is required to conduct their work. This structure includes site-essential, site-by-design, field-based and remote-by-design jobs. The occupancy type that you are assigned is determined by the nature and responsibilities of your roleSite-essential roles require 100% of shifts onsite at your assigned facility. Site-by-design roles may be eligible for a hybrid work model with at least 50% onsite at your assigned facility. For these roles, onsite presence is considered an essential job function and is critical to collaboration, innovation, productivity, and a positive Company culture. For field-based and remote-by-design roles the ability to physically travel to visit customers, patients or business partners and to attend meetings on behalf of BMS as directed is an essential job function.BMS is dedicated to ensuring that people with disabilities can excel through a transparent recruitment process, reasonable workplace accommodations/adjustments and ongoing support in their roles. Applicants can request a reasonable workplace accommodation/adjustment prior to accepting a job offer. If you require reasonable accommodations/adjustments in completing this application, or in any part of the recruitment process, direct your inquiries to adastaffingsupport@bms.com . Visit careers.bms.com/ eeo -accessibility to access our complete Equal Employment Opportunity statement.BMS cares about your well-being and the well-being of our staff, customers, patients, and communities. As a result, the Company strongly recommends that all employees be fully vaccinated for Covid-19 and keep up to date with Covid-19 boosters.BMS will consider for employment qualified applicants with arrest and conviction records, pursuant to applicable laws in your area.If you live in or expect to work from Los Angeles County if hired for this position, please visit this page for important additional information https //careers.bms.com/california-residents/Any data processed in connection with role applications will be treated in accordance with applicable data privacy policies and regulations.",
      "requirements": [
        "required skill, and the geographic location of the job",
        "required skills, where the job is performed, the employee's work schedule, job-related knowledge, and experie",
        "required to conduct their work",
        "essential roles require 100% of shifts onsite at your assigned facility",
        "essential job function and is critical to collaboration, innovation, productivity, and a positive Company cult",
        "essential job function",
        "Bachelor's or Master's degree in data analytics, engineeri",
        "Experience with platforms or applications such as SAP, Benchling, LIMS, Veeva Quality Vault, ME"
      ],
      "job_type": "Full-time",
      "skills": [
        "Git",
        "Github",
        "Tableau",
        "Sql",
        "Go",
        "Python",
        "Scala",
        "Ai",
        "Aws",
        "R"
      ],
      "posted_date": "2025-09-09",
      "job_url": "https://www.linkedin.com/jobs/view/data-scientist-co-op-at-bristol-myers-squibb-4298164055?position=6&pageNum=5&refId=2WB8U2Bvlq52Z47txPXXIA%3D%3D&trackingId=AHg2Y6qzzTok2AS30rZTbQ%3D%3D",
      "salary": "",
      "category": "Data Science & Analytics",
      "is_trusted_company": true,
      "experience_level": "Mid Level",
      "employment_type": "Full-time"
    }
  ]
}